wind_pypcd/__init__.py
wind_pypcd/nea_pc_format.py
wind_pypcd/numpy_pc2.py
wind_pypcd/pdutil.py
wind_pypcd/pypcd.py
wind_pypcd/sautil.py
wind_pypcd/tests/__init__.py
wind_pypcd/tests/test_pypcd.py
wind_pypcd-0.4.0.dist-info/licenses/LICENSE
wind_pypcd-0.4.0.dist-info/METADATA
wind_pypcd-0.4.0.dist-info/WHEEL
wind_pypcd-0.4.0.dist-info/entry_points.txt
wind_pypcd-0.4.0.dist-info/top_level.txt
wind_pypcd-0.4.0.dist-info/RECORD
