Metadata-Version: 2.4
Name: wind-pypcd
Version: 0.4.0
Summary: tools for pcd files
Author-email: windzu <windzu1@gmail.com>
License: MIT
Keywords: pcd,point cloud,lidar,tools
Classifier: Development Status :: 3 - Alpha
Classifier: Intended Audience :: Developers
Classifier: License :: OSI Approved :: MIT License
Classifier: Natural Language :: English
Classifier: Programming Language :: Python :: 3
Classifier: Programming Language :: Python :: 3.8
Classifier: Programming Language :: Python :: 3.9
Classifier: Programming Language :: Python :: 3.10
Classifier: Programming Language :: Python :: 3.12
Requires-Python: !=3.11.*,<3.13,>=3.8
License-File: LICENSE
Requires-Dist: numpy
Requires-Dist: python-lzf
Dynamic: license-file
